powerline_podman/__init__.py
powerline_podman/segments.py
powerline_podman-1.0.4.dist-info/METADATA
powerline_podman-1.0.4.dist-info/WHEEL
powerline_podman-1.0.4.dist-info/licenses/LICENSE
powerline_podman-1.0.4.dist-info/RECORD
