Metadata-Version: 2.4
Name: powerline-podman
Version: 1.0.4
Summary: A custom Powerline segment for displaying the current state of Podman containers
Project-URL: Homepage, https://github.com/j4ckofalltrades/powerline-podman
Project-URL: Repository, https://github.com/j4ckofalltrades/powerline-podman
Project-URL: Bug Tracker, https://github.com/j4ckofalltrades/powerline-podman/issues
Author-email: Jordan Duabe <me@jduabe.dev>
License: MIT
License-File: LICENSE
Keywords: podman,powerline
Requires-Python: >=3.10
Requires-Dist: podman>=5.5.0
Requires-Dist: powerline-status>=2.7
